cronradar_celery/__init__.py
cronradar_celery/discovery.py
cronradar_celery/monitors.py
cronradar_celery/utils.py
cronradar_celery-0.0.4.dist-info/licenses/LICENSE
cronradar_celery-0.0.4.dist-info/METADATA
cronradar_celery-0.0.4.dist-info/WHEEL
cronradar_celery-0.0.4.dist-info/top_level.txt
cronradar_celery-0.0.4.dist-info/RECORD
