Metadata-Version: 2.4
Name: cronradar-celery
Version: 0.0.4
Summary: Automatic monitoring for Celery periodic tasks. Monitor selective tasks or all tasks with auto-discovery.
Home-page: https://github.com/cronradar/cronradar-celery
Author: Administrator
Author-email: contact@cronradar.com
License: Proprietary
Project-URL: Documentation, https://cronradar.com/docs
Project-URL: Source, https://github.com/cronradar/cronradar-celery
Project-URL: Tracker, https://github.com/cronradar/cronradar-celery/issues
Keywords: celery monitoring cron task beat periodic auto-discovery cronradar
Classifier: Development Status :: 5 - Production/Stable
Classifier: Intended Audience :: Developers
Classifier: License :: Other/Proprietary License
Classifier: Operating System :: OS Independent
Classifier: Programming Language :: Python :: 3
Classifier: Programming Language :: Python :: 3.8
Classifier: Programming Language :: Python :: 3.9
Classifier: Programming Language :: Python :: 3.10
Classifier: Programming Language :: Python :: 3.11
Classifier: Programming Language :: Python :: 3.12
Classifier: Topic :: Software Development :: Libraries :: Python Modules
Classifier: Topic :: System :: Monitoring
Requires-Python: >=3.8
License-File: LICENSE
Requires-Dist: cronradar>=0.0.4
Requires-Dist: celery>=5.0.0
Dynamic: author
Dynamic: author-email
Dynamic: classifier
Dynamic: description
Dynamic: description-content-type
Dynamic: home-page
Dynamic: keywords
Dynamic: license
Dynamic: license-file
Dynamic: project-url
Dynamic: requires-dist
Dynamic: requires-python
Dynamic: summary
